README.md
setup.cfg
setup.py
csv_map_converter/__init__.py
csv_map_converter/converter.py
csv_map_converter.egg-info/PKG-INFO
csv_map_converter.egg-info/SOURCES.txt
csv_map_converter.egg-info/dependency_links.txt
csv_map_converter.egg-info/top_level.txt
csv_map_converter/models/__init__.py
csv_map_converter/models/fields/__init__.py
csv_map_converter/models/fields/base.py
csv_map_converter/models/fields/model_descriptor.py
csv_map_converter/parsers/__init__.py
csv_map_converter/parsers/parser.py
csv_map_converter/parsers/result.py
tests/__init__.py
tests/test_converter.py
tests/test_converter_model.py
tests/test_fields.py