Metadata-Version: 1.0
Name: csv-map-converter
Version: 1.2.2
Summary: It is csv converter to be able to get multi-values.
Home-page: https://github.com/eHanlin/csv-map-converter
Author: Sparrow Jang
Author-email: sparrow.jang@gmail.com
License: UNKNOWN
Platform: UNKNOWN
